bnf_api/__init__.py
bnf_api/api.py
bnf_api/config.py
bnf_api/search.py
bnf_api/sequential_reporting.py
iflow_mcp_mcp_bibliotheque_nationale_de_france-0.1.1.dist-info/METADATA
iflow_mcp_mcp_bibliotheque_nationale_de_france-0.1.1.dist-info/WHEEL
iflow_mcp_mcp_bibliotheque_nationale_de_france-0.1.1.dist-info/entry_points.txt
iflow_mcp_mcp_bibliotheque_nationale_de_france-0.1.1.dist-info/top_level.txt
iflow_mcp_mcp_bibliotheque_nationale_de_france-0.1.1.dist-info/RECORD
