Metadata-Version: 2.4
Name: iflow-mcp_mcp-bibliotheque_nationale_de_france
Version: 0.1.1
Summary: Un serveur MCP pour accéder à l'API Gallica de la Bibliothèque nationale de France (BnF)
Author-email: Kryzo <kryzo@example.com>
License: MIT
Project-URL: Homepage, https://github.com/iflow-mcp/mcp-bibliotheque_nationale_de_france
Project-URL: Repository, https://github.com/iflow-mcp/mcp-bibliotheque_nationale_de_france
Classifier: Development Status :: 3 - Alpha
Classifier: Intended Audience :: Developers
Classifier: License :: OSI Approved :: MIT License
Classifier: Programming Language :: Python :: 3
Classifier: Programming Language :: Python :: 3.8
Classifier: Programming Language :: Python :: 3.9
Classifier: Programming Language :: Python :: 3.10
Classifier: Programming Language :: Python :: 3.11
Requires-Python: >=3.8
Requires-Dist: requests==2.31.0
Requires-Dist: fastmcp==0.1.0
